myfootballdata/__init__.py
myfootballdata/baseApi.py
myfootballdata/baseUrl.py
myfootballdata/exceptions.py
myfootballdata/myhttp.py
ifyfootballdata-0.0.1.dist-info/METADATA
ifyfootballdata-0.0.1.dist-info/WHEEL
ifyfootballdata-0.0.1.dist-info/top_level.txt
ifyfootballdata-0.0.1.dist-info/RECORD
