Metadata-Version: 2.1
Name: ifyfootballdata
Version: 0.0.1
Summary: Football data package for https://www.football-data.org
Home-page: https://github.com/Jeon316upzx/football-data
Author: Ifeanyi Anuebunwa
Author-email: jeon316@icloud.com
License: Apache License 2.0
Keywords: football-data,premier league,La liga,Serie A,Championship
Platform: UNKNOWN
Classifier: Development Status :: 3 - Alpha
Classifier: Intended Audience :: Developers
Classifier: Programming Language :: Python :: 2
Classifier: Programming Language :: Python :: 3
Classifier: Operating System :: MacOS :: MacOS X
Classifier: Operating System :: Microsoft :: Windows
